ValiDecor/LICENSE
ValiDecor/README.md
ValiDecor/__init__.py
ValiDecor/core.py
ValiDecor/validators.py
ValiDecor-1.0.4.dist-info/LICENSE
ValiDecor-1.0.4.dist-info/METADATA
ValiDecor-1.0.4.dist-info/WHEEL
ValiDecor-1.0.4.dist-info/top_level.txt
ValiDecor-1.0.4.dist-info/RECORD
