Metadata-Version: 2.1
Name: ValiDecor
Version: 1.0.4
Summary: Decorated, Annotated, Validated
Author-email: giladooshlon <giladrv@gmail.com>
License: MIT License
Project-URL: Homepage, https://github.com/giladrv/validecor
Keywords: validation,decorator,lambda
Classifier: License :: OSI Approved :: MIT License
Classifier: Programming Language :: Python
Classifier: Programming Language :: Python :: 3
Requires-Python: >=3.9
License-File: LICENSE
